Metadata-Version: 1.1
Name: phjs-manager
Version: 0.0.7
Summary: A simple python interface to docker which runs containers
Home-page: https://github.com/michey/phjs-manager
Author: michey
Author-email: mixeyy@gmail.com
License: MIT
Keywords: docker phantomjs
Platform: UNKNOWN
Classifier: Development Status :: 3 - Alpha
Classifier: Intended Audience :: Developers
Classifier: Topic :: Software Development :: Build Tools
Classifier: License :: OSI Approved :: MIT License
Classifier: Programming Language :: Python :: 2.7
